AUTHORS.rst
CONTRIBUTING.rst
HISTORY.rst
LICENSE
MANIFEST.in
README.rst
setup.cfg
setup.py
docs/Makefile
docs/authors.rst
docs/conf.py
docs/contributing.rst
docs/history.rst
docs/index.rst
docs/installation.rst
docs/make.bat
docs/readme.rst
docs/usage.rst
pyloggo/__init__.py
pyloggo/pyloggo.py
pyloggo.egg-info/PKG-INFO
pyloggo.egg-info/SOURCES.txt
pyloggo.egg-info/dependency_links.txt
pyloggo.egg-info/not-zip-safe
pyloggo.egg-info/requires.txt
pyloggo.egg-info/top_level.txt
tests/__init__.py
tests/test_handlers.py
tests/test_pyloggo.py