Metadata-Version: 1.1
Name: pyloggo
Version: 0.2.0
Summary: Python logging handlers
Home-page: https://github.com/mhetrerajat/pyloggo
Author: Rajat Mhetre
Author-email: mhetrerajat@gmail.com
License: MIT license
Keywords: pyloggo
Platform: UNKNOWN
Classifier: Development Status :: 2 - Pre-Alpha
Classifier: Intended Audience :: Developers
Classifier: License :: OSI Approved :: MIT License
Classifier: Natural Language :: English
Classifier: Programming Language :: Python :: 3
Classifier: Programming Language :: Python :: 3.3
Classifier: Programming Language :: Python :: 3.4
Classifier: Programming Language :: Python :: 3.5
